x2y/__init__.py
x2y/logger.py
x2y/options.py
x2y/x2y.py
x2y-0.1.0.dist-info/DESCRIPTION.rst
x2y-0.1.0.dist-info/entry_points.txt
x2y-0.1.0.dist-info/METADATA
x2y-0.1.0.dist-info/metadata.json
x2y-0.1.0.dist-info/RECORD
x2y-0.1.0.dist-info/top_level.txt
x2y-0.1.0.dist-info/WHEEL
