Metadata-Version: 2.0
Name: x2y
Version: 0.1.0
Summary: x2y: convert line ending between DOS, Mac and Unix
Home-page: https://github.com/bnomis/x2y
Author: Simon Blanchard
Author-email: bnomis@gmail.com
License: MIT
Keywords: text,conversion
Platform: macosx
Platform: linux
Platform: unix
Classifier: Development Status :: 5 - Production/Stable
Classifier: Environment :: Console
Classifier: Intended Audience :: Developers
Classifier: License :: OSI Approved :: MIT License
Classifier: Natural Language :: English
Classifier: Operating System :: POSIX
Classifier: Programming Language :: Python :: 2.7
Classifier: Programming Language :: Python :: 3.4
Classifier: Topic :: Office/Business :: Office Suites
Classifier: Topic :: Text Processing
Classifier: Topic :: Utilities
